conbench/__init__.py
conbench/_version.py
conbench/buildinfo.py
conbench/cli.py
conbench/config.py
conbench/db.py
conbench/extensions.py
conbench/gunicorn-conf.py
conbench/hacks.py
conbench/logger.py
conbench/machine_info.py
conbench/metrics.py
conbench/runner.py
conbench/units.py
conbench/util.py
conbench/api/__init__.py
conbench/api/_docs.py
conbench/api/_endpoint.py
conbench/api/_errors.py
conbench/api/_examples.py
conbench/api/_google.py
conbench/api/_resp.py
conbench/api/auth.py
conbench/api/commits.py
conbench/api/compare.py
conbench/api/contexts.py
conbench/api/hardware.py
conbench/api/history.py
conbench/api/index.py
conbench/api/info.py
conbench/api/results.py
conbench/api/runs.py
conbench/api/users.py
conbench/app/__init__.py
conbench/app/_endpoint.py
conbench/app/_plots.py
conbench/app/_util.py
conbench/app/auth.py
conbench/app/batches.py
conbench/app/compare.py
conbench/app/hardware.py
conbench/app/index.py
conbench/app/results.py
conbench/app/robots.py
conbench/app/runs.py
conbench/app/users.py
conbench/entities/__init__.py
conbench/entities/_comparator.py
conbench/entities/_entity.py
conbench/entities/benchmark_result.py
conbench/entities/case.py
conbench/entities/commit.py
conbench/entities/compare.py
conbench/entities/context.py
conbench/entities/hardware.py
conbench/entities/history.py
conbench/entities/info.py
conbench/entities/run.py
conbench/entities/user.py
conbench/tests/__init__.py
conbench/tests/conftest.py
conbench/tests/helpers.py
conbench/tests/populate_local_conbench.py
conbench/tests/test_util.py
conbench/tests/test_version.py
conbench/tests/api/__init__.py
conbench/tests/api/_asserts.py
conbench/tests/api/_expected_docs.py
conbench/tests/api/_fixtures.py
conbench/tests/api/test_auth.py
conbench/tests/api/test_commits.py
conbench/tests/api/test_compare.py
conbench/tests/api/test_contexts.py
conbench/tests/api/test_docs.py
conbench/tests/api/test_hardware.py
conbench/tests/api/test_history.py
conbench/tests/api/test_index.py
conbench-2023.4.10.dist-info/LICENSE
conbench-2023.4.10.dist-info/METADATA
conbench-2023.4.10.dist-info/WHEEL
conbench-2023.4.10.dist-info/entry_points.txt
conbench-2023.4.10.dist-info/top_level.txt
conbench-2023.4.10.dist-info/RECORD
