Metadata-Version: 2.1
Name: conbench
Version: 2023.4.10
Summary: Continuous Benchmarking (CB) Framework
Home-page: https://github.com/conbench/conbench
Maintainer: Apache Arrow Developers
Maintainer-email: dev@arrow.apache.org
Classifier: Programming Language :: Python :: 3.8
Classifier: License :: OSI Approved :: MIT License
Requires-Python: >=3.8
License-File: LICENSE
Requires-Dist: click
Requires-Dist: numpy
Requires-Dist: psutil
Requires-Dist: py-cpuinfo
Requires-Dist: pytest (>=7.0.0)
Requires-Dist: PyYAML
Requires-Dist: requests
Provides-Extra: dev
Requires-Dist: alembic ; extra == 'dev'
Requires-Dist: apispec ; extra == 'dev'
Requires-Dist: apispec-webframeworks ; extra == 'dev'
Requires-Dist: bokeh ; extra == 'dev'
Requires-Dist: click ; extra == 'dev'
Requires-Dist: dacite ; extra == 'dev'
Requires-Dist: email-validator ; extra == 'dev'
Requires-Dist: Flask ; extra == 'dev'
Requires-Dist: Flask-Bootstrap ; extra == 'dev'
Requires-Dist: Flask-Login ; extra == 'dev'
Requires-Dist: flask-swagger-ui ; extra == 'dev'
Requires-Dist: Flask-WTF ; extra == 'dev'
Requires-Dist: gitpython ; extra == 'dev'
Requires-Dist: gunicorn ; extra == 'dev'
Requires-Dist: marshmallow ; extra == 'dev'
Requires-Dist: numpy ; extra == 'dev'
Requires-Dist: oauthlib ; extra == 'dev'
Requires-Dist: openapi-spec-validator ; extra == 'dev'
Requires-Dist: orjson ; extra == 'dev'
Requires-Dist: pandas ; extra == 'dev'
Requires-Dist: prometheus-client ; extra == 'dev'
Requires-Dist: prometheus-flask-exporter ; extra == 'dev'
Requires-Dist: psutil ; extra == 'dev'
Requires-Dist: psycopg2 ; extra == 'dev'
Requires-Dist: py-cpuinfo ; extra == 'dev'
Requires-Dist: pytest (>=7.0.0) ; extra == 'dev'
Requires-Dist: python-dotenv ; extra == 'dev'
Requires-Dist: PyYAML ; extra == 'dev'
Requires-Dist: requests ; extra == 'dev'
Requires-Dist: tenacity ; extra == 'dev'
Requires-Dist: SQLAlchemy (>=2) ; extra == 'dev'
Requires-Dist: black ; extra == 'dev'
Requires-Dist: bs4 ; extra == 'dev'
Requires-Dist: coveralls ; extra == 'dev'
Requires-Dist: flake8 ; extra == 'dev'
Requires-Dist: isort ; extra == 'dev'
Requires-Dist: lxml ; extra == 'dev'
Requires-Dist: pylint ; extra == 'dev'
Requires-Dist: mypy ; extra == 'dev'
Requires-Dist: myst-parser ; extra == 'dev'
Requires-Dist: sphinx ; extra == 'dev'
Requires-Dist: sphinx-autodoc-typehints ; extra == 'dev'
Requires-Dist: types-beautifulsoup4 ; extra == 'dev'
Requires-Dist: types-psutil ; extra == 'dev'
Requires-Dist: types-PyYAML ; extra == 'dev'
Requires-Dist: types-requests ; extra == 'dev'
Requires-Dist: types-oauthlib ; extra == 'dev'
Requires-Dist: types-Flask ; extra == 'dev'
Provides-Extra: server
Requires-Dist: alembic ; extra == 'server'
Requires-Dist: apispec ; extra == 'server'
Requires-Dist: apispec-webframeworks ; extra == 'server'
Requires-Dist: bokeh ; extra == 'server'
Requires-Dist: click ; extra == 'server'
Requires-Dist: dacite ; extra == 'server'
Requires-Dist: email-validator ; extra == 'server'
Requires-Dist: Flask ; extra == 'server'
Requires-Dist: Flask-Bootstrap ; extra == 'server'
Requires-Dist: Flask-Login ; extra == 'server'
Requires-Dist: flask-swagger-ui ; extra == 'server'
Requires-Dist: Flask-WTF ; extra == 'server'
Requires-Dist: gitpython ; extra == 'server'
Requires-Dist: gunicorn ; extra == 'server'
Requires-Dist: marshmallow ; extra == 'server'
Requires-Dist: numpy ; extra == 'server'
Requires-Dist: oauthlib ; extra == 'server'
Requires-Dist: openapi-spec-validator ; extra == 'server'
Requires-Dist: orjson ; extra == 'server'
Requires-Dist: pandas ; extra == 'server'
Requires-Dist: prometheus-client ; extra == 'server'
Requires-Dist: prometheus-flask-exporter ; extra == 'server'
Requires-Dist: psutil ; extra == 'server'
Requires-Dist: psycopg2 ; extra == 'server'
Requires-Dist: py-cpuinfo ; extra == 'server'
Requires-Dist: pytest (>=7.0.0) ; extra == 'server'
Requires-Dist: python-dotenv ; extra == 'server'
Requires-Dist: PyYAML ; extra == 'server'
Requires-Dist: requests ; extra == 'server'
Requires-Dist: tenacity ; extra == 'server'
Requires-Dist: SQLAlchemy (>=2) ; extra == 'server'
